wtv/__init__.py
wtv/cli.py
wtv/ion_selection.py
wtv/utils.py
wtv-0.1.0.dist-info/LICENSE
wtv-0.1.0.dist-info/METADATA
wtv-0.1.0.dist-info/WHEEL
wtv-0.1.0.dist-info/entry_points.txt
wtv-0.1.0.dist-info/RECORD
