Metadata-Version: 2.3
Name: wtv
Version: 0.1.0
Summary: A library and CLI for ion selection in mass spectrometry data.
License: GPL-3.0
Author: RECETOX
Requires-Python: >=3.10,<3.13
Classifier: License :: OSI Approved :: GNU General Public License v3 (GPLv3)
Classifier: Programming Language :: Python :: 3
Classifier: Programming Language :: Python :: 3.10
Classifier: Programming Language :: Python :: 3.11
Classifier: Programming Language :: Python :: 3.12
Requires-Dist: matchms (>=0.30.2,<0.31.0)
Requires-Dist: numpy (>=2,<3)
Requires-Dist: pandas (>=2.2.3,<3.0.0)
